{
  "battles": [
    {
      "index": 1,
      "title": "バケツでワンパン？",
      "code": "RHKG-S62A-2QSU-K49P",
      "memo": "バケツってワンパン出来ましたっけ？\r\nそこら辺疎くって分かりません",
      "playlist": "ラグかチート",
      "created_at": "2025-11-17T14:00:54.754943Z",
      "splatoon_version": "10.1.0",
      "screenshot_paths": [
        "users/642335102055088128/media/battle_1_screenshot_1.png"
      ],
      "video_paths": [
        "users/642335102055088128/media/battle_1_video_2.mov",
        "users/642335102055088128/media/battle_1_video_1.mov"
      ],
      "screenshot_path": "users/642335102055088128/media/battle_1_screenshot_1.png",
      "video_path": "users/642335102055088128/media/battle_1_video_1.mov",
      "likes": 2,
      "comments": [],
      "liked_by": [
        "642335102055088128"
      ]
    },
    {
      "index": 2,
      "title": "ガチホコバトル",
      "code": "RMM4-7ANF-8K4H-NK49",
      "memo": "アドバイスほしいです\r\n立ち回り方など\r\n一応Sではあるんですが、味方依存の勝利になっている気がするという感じがします",
      "playlist": "アドバイス",
      "created_at": "2025-11-17T14:43:58.484480Z",
      "splatoon_version": "10.1.0",
      "screenshot_paths": [
        "users/642335102055088128/media/auto_2_1763462049_1.jpeg"
      ],
      "video_paths": null,
      "screenshot_path": "users/642335102055088128/media/auto_2_1763462049_1.jpeg",
      "video_path": null,
      "likes": 0,
      "liked_by": [],
      "comments": []
    },
    {
      "index": 3,
      "title": "ガチホコバトル",
      "code": "RDG0-8T6W-24E6-BL4F",
      "memo": "上手くなるほうほうや立ち回り方、アドバイスください！",
      "playlist": "アドバイス",
      "created_at": "2025-11-17T15:01:32.944846Z",
      "splatoon_version": "10.1.0",
      "screenshot_paths": [
        "users/642335102055088128/media/auto_3_1763462235_1.jpeg"
      ],
      "video_paths": null,
      "screenshot_path": "users/642335102055088128/media/auto_3_1763462235_1.jpeg",
      "video_path": null,
      "likes": 0,
      "liked_by": [],
      "comments": []
    },
    {
      "index": 4,
      "title": "ガチホコバトル",
      "code": "R8R6-PGL5-1XC6-CD86",
      "memo": "戦犯しました\r\nどのように動けばよかったのか教えてください！\r\n\r\n最後のホコも止められなかったのが悔しいです！",
      "playlist": "アドバイス",
      "created_at": "2025-11-17T15:03:07.873871Z",
      "splatoon_version": "10.1.0",
      "screenshot_paths": [
        "users/642335102055088128/media/auto_4_1763462233_1.jpeg"
      ],
      "video_paths": null,
      "screenshot_path": "users/642335102055088128/media/auto_4_1763462233_1.jpeg",
      "video_path": null,
      "likes": 0,
      "liked_by": [],
      "comments": []
    },
    {
      "index": 5,
      "title": "ガチホコそこ乗れるの？？？",
      "code": "R6FD-V448-CKJ2-Q5K2",
      "memo": "乗れることに気がつかなくて、意識しておらずノックアウト負け！\r\nごめんなさい。",
      "playlist": "",
      "created_at": "2025-11-17T15:44:01.315195Z",
      "splatoon_version": "10.1.0",
      "screenshot_paths": [
        "users/642335102055088128/media/auto_5_1763462419_1.jpeg"
      ],
      "video_paths": null,
      "screenshot_path": "users/642335102055088128/media/auto_5_1763462419_1.jpeg",
      "video_path": null,
      "likes": 0,
      "liked_by": [],
      "comments": []
    },
    {
      "index": 6,
      "title": "ガチホコバトル 個人的に上手くいった",
      "code": "RG4K-TMJ2-WW89-4VDC",
      "memo": "自分的にはうまくできたと思います！\r\nもっとこうすればいいよ〜などアドバイスがあれば教えてくださいっ！",
      "playlist": "",
      "created_at": "2025-11-18T12:54:28.177619Z",
      "splatoon_version": "10.1.0",
      "screenshot_paths": [
        "users/642335102055088128/media/auto_6_1763472502_1.jpg"
      ],
      "video_paths": null,
      "screenshot_path": "users/642335102055088128/media/auto_6_1763472502_1.jpg",
      "video_path": null,
      "likes": 0,
      "liked_by": [],
      "comments": []
    },
    {
      "index": 7,
      "title": "ガチアサリ-何かかっこいいシーン",
      "code": "R37F-JDLL-C31A-UJYL",
      "memo": "ガチアサリが画面に向かって飛んできました！\r\n何かかっこいい？",
      "playlist": "",
      "created_at": "2025-11-19T08:58:42.976237Z",
      "splatoon_version": "10.1.0",
      "screenshot_paths": null,
      "video_paths": [
        "users/642335102055088128/media/battle_7_video_1.mov"
      ],
      "screenshot_path": null,
      "video_path": "users/642335102055088128/media/battle_7_video_1.mov",
      "likes": 0,
      "liked_by": [],
      "comments": []
    },
    {
      "index": 8,
      "title": "ワンパンできるの…？",
      "code": "RQ4F-E3YM-2EHC-YL9F",
      "memo": "ラインマーカーも当たってワンパンってことかな…？\r\nわからない。",
      "playlist": "",
      "created_at": "2025-11-19T09:00:46.999685Z",
      "splatoon_version": "10.1.0",
      "screenshot_paths": null,
      "video_paths": [
        "users/642335102055088128/media/battle_8_video_1.mov"
      ],
      "screenshot_path": null,
      "video_path": "users/642335102055088128/media/battle_8_video_1.mov",
      "likes": 0,
      "liked_by": [],
      "comments": []
    }
  ]
}